aliyun_sdk_core/__init__.py
aliyun_sdk_core/client.py
aliyun_sdk_core/common.py
aliyun_sdk_core/oss.py
zy_aliyun_python_sdk_core-1.0.0.dist-info/LICENSE
zy_aliyun_python_sdk_core-1.0.0.dist-info/METADATA
zy_aliyun_python_sdk_core-1.0.0.dist-info/WHEEL
zy_aliyun_python_sdk_core-1.0.0.dist-info/top_level.txt
zy_aliyun_python_sdk_core-1.0.0.dist-info/RECORD
