Metadata-Version: 2.1
Name: zy-aliyun-python-sdk-core
Version: 1.0.0
Summary: sample sdk for aliyun
Home-page: https://github.com/munan921/zy-aliyun-python-sdk
Author: munan921
Author-email: immndev@hotmail.com
License: MIT
Classifier: Programming Language :: Python :: 3
Classifier: License :: OSI Approved :: MIT License
Classifier: Operating System :: OS Independent
License-File: LICENSE
Requires-Dist: certifi>=2019.6.16
Requires-Dist: chardet>=3.0.4
Requires-Dist: decorator>=4.4.0
Requires-Dist: idna>=2.8
Requires-Dist: requests>=2.22.0
Requires-Dist: retry>=0.9.2
Requires-Dist: urllib3>=1.25.3
Requires-Dist: xmltodict>=0.12.0
